tv80_lib/8085_instr_set.v
//MCS-85 instruction set   
`define MOV_B_B 8'b01000000
`define MOV_B_C 8'b01000001
`define MOV_B_D 8'b01000010
`define MOV_B_E 8'b01000011
`define MOV_B_H 8'b01000100
`define MOV_B_L 8'b01000101
`define MOV_B_M 8'b01000110
`define MOV_B_A 8'b01000111
`define MOV_C_B 8'b01001000
`define MOV_C_C 8'b01001001
`define MOV_C_D 8'b01001010
`define MOV_C_E 8'b01001011
`define MOV_C_H 8'b01001100
`define MOV_C_L 8'b01001101
`define MOV_C_M 8'b01001110
`define MOV_C_A 8'b01001111
`define MOV_D_B 8'b01010000
`define MOV_D_C 8'b01010001
`define MOV_D_D 8'b01010010
`define MOV_D_E 8'b01010011
`define MOV_D_H 8'b01010100
`define MOV_D_L 8'b01010101
`define MOV_D_M 8'b01010110
`define MOV_D_A 8'b01010111
`define MOV_E_B 8'b01011000
`define MOV_E_C 8'b01011001
`define MOV_E_D 8'b01011010
`define MOV_E_E 8'b01011011
`define MOV_E_H 8'b01011100
`define MOV_E_L 8'b01011101
`define MOV_E_M 8'b01011110
`define MOV_E_A 8'b01011111
`define MOV_H_B 8'b01100000
`define MOV_H_C 8'b01100001
`define MOV_H_D 8'b01100010
`define MOV_H_E 8'b01100011
`define MOV_H_H 8'b01100100
`define MOV_H_L 8'b01100101
`define MOV_H_M 8'b01100110
`define MOV_H_A 8'b01100111
`define MOV_L_B 8'b01101000
`define MOV_L_C 8'b01101001
`define MOV_L_D 8'b01101010
`define MOV_L_E 8'b01101011
`define MOV_L_H 8'b01101100
`define MOV_L_L 8'b01101101
`define MOV_L_M 8'b01101110
`define MOV_L_A 8'b01101111
`define MOV_M_B 8'b01110000
`define MOV_M_C 8'b01110001
`define MOV_M_D 8'b01110010
`define MOV_M_E 8'b01110011
`define MOV_M_H 8'b01110100
`define MOV_M_L 8'b01110101
`define MOV_M_M 8'b01110110
`define MOV_M_A 8'b01110111
`define MOV_A_B 8'b01111000
`define MOV_A_C 8'b01111001
`define MOV_A_D 8'b01111010
`define MOV_A_E 8'b01111011
`define MOV_A_H 8'b01111100
`define MOV_A_L 8'b01111101
`define MOV_A_M 8'b01111110
`define MOV_A_A 8'b01111111
`define MVI_B	8'b00000110
`define MVI_C	8'b00001110
`define MVI_D	8'b00010110
`define MVI_E	8'b00011110
`define MVI_H	8'b00100110
`define MVI_L	8'b00101110
`define MVI_M	8'b00110110
`define MVI_A	8'b00111110
`define LXI_B	8'b00000001
`define LXI_D	8'b00010001
`define LXI_H	8'b00100001
`define LXI_SP	8'b00110001
`define LDA		8'b00111010
`define STA		8'b00110010
`define LHLD	8'b00101010
`define SHLD	8'b00100010
`define LDAX_B	8'b00001010
`define LDAX_D	8'b00011010
`define STAX_B	8'b00000010
`define STAX_D	8'b00010010
`define XCHG	8'b11101011
`define ADD_B	8'b10000000
`define ADD_C	8'b10000001
`define ADD_D	8'b10000010
`define ADD_E	8'b10000011
`define ADD_H	8'b10000100
`define ADD_L	8'b10000101
`define ADD_M	8'b10000110
`define ADD_A	8'b10000111
`define ADC_B	8'b10001000
`define ADC_C	8'b10001001
`define ADC_D	8'b10001010
`define ADC_E	8'b10001011
`define ADC_H	8'b10001100
`define ADC_L	8'b10001101
`define ADC_M	8'b10001110
`define ADC_A	8'b10001111
`define SUB_B	8'b10010000
`define SUB_C	8'b10010001
`define SUB_D	8'b10010010
`define SUB_E	8'b10010011
`define SUB_H	8'b10010100
`define SUB_L	8'b10010101
`define SUB_M	8'b10010110
`define SUB_A	8'b10010111
`define SBB_B	8'b10011000
`define SBB_C	8'b10011001
`define SBB_D	8'b10011010
`define SBB_E	8'b10011011
`define SBB_H	8'b10011100
`define SBB_L	8'b10011101
`define SBB_M	8'b10011110
`define SBB_A	8'b10011111
`define ANA_B	8'b10100000
`define ANA_C	8'b10100001
`define ANA_D	8'b10100010
`define ANA_E	8'b10100011
`define ANA_H	8'b10100100
`define ANA_L	8'b10100101
`define ANA_M	8'b10100110
`define ANA_A	8'b10100111
`define XRA_B	8'b10101000
`define XRA_C	8'b10101001
`define XRA_D	8'b10101010
`define XRA_E	8'b10101011
`define XRA_H	8'b10101100
`define XRA_L	8'b10101101
`define XRA_M	8'b10101110
`define XRA_A	8'b10101111
`define ORA_B	8'b10110000
`define ORA_C	8'b10110001
`define ORA_D	8'b10110010
`define ORA_E	8'b10110011
`define ORA_H	8'b10110100
`define ORA_L	8'b10110101
`define ORA_M	8'b10110110
`define ORA_A	8'b10110111
`define CMP_B	8'b10111000
`define CMP_C	8'b10111001
`define CMP_D	8'b10111010
`define CMP_E	8'b10111011
`define CMP_H	8'b10111100
`define CMP_L	8'b10111101
`define CMP_M	8'b10111110
`define CMP_A	8'b10111111
`define ADI		8'b11000110
`define ACI		8'b11001110
`define SUI		8'b11010110
`define SBI		8'b11011110
`define ANI		8'b11100110
`define XRI		8'b11101110
`define ORI		8'b11110110
`define CPI		8'b11111110
`define DAA		8'b00100111
`define RLC		8'b00000111
`define RRC		8'b00001111
`define RAL		8'b00010111
`define RAR		8'b00011111
`define CMA		8'b00101111
`define STC		8'b00110111
`define CMC		8'b00111111
`define INR_B	8'b00000100
`define INR_C	8'b00001100
`define INR_D	8'b00010100
`define INR_E	8'b00011100
`define INR_H	8'b00100100
`define INR_L	8'b00101100
`define INR_M	8'b00110100
`define INR_A	8'b00111100
`define DCR_B	8'b00000101
`define DCR_C	8'b00001101
`define DCR_D	8'b00010101
`define DCR_E	8'b00011101
`define DCR_H	8'b00100101
`define DCR_L	8'b00101101
`define DCR_M	8'b00110101
`define DCR_A	8'b00111101
`define INX_B	8'b00000011
`define INX_D	8'b00010011
`define INX_H	8'b00100011
`define INX_SP	8'b00110011
`define DCX_B	8'b00001011
`define DCX_D	8'b00011011
`define DCX_H	8'b00101011
`define DCX_SP	8'b00111011
`define DAD_B	8'b00001001
`define DAD_D	8'b00011001
`define DAD_H	8'b00101001
`define DAD_SP	8'b00111001
`define JMP		8'b11000011
`define JNZ		8'b11000010
`define JZ		8'b11001010
`define JNC		8'b11010010
`define JC		8'b11011010
`define JPO		8'b11100010
`define JPE		8'b11101010
`define JP		8'b11110010
`define JM		8'b11111010
`define CALL	8'b11001101
`define CNZ		8'b11000100
`define CZ		8'b11001100
`define CNC		8'b11010100
`define CC		8'b11011100
`define CPO		8'b11100100
`define CPE		8'b11101100
`define CP		8'b11110100
`define CM		8'b11111100
`define RET		8'b11001001
`define RNZ		8'b11000000
`define RZ		8'b11001000
`define RNC		8'b11010000
`define RC		8'b11011000
`define RPO		8'b11100000
`define RPE		8'b11101000
`define RP		8'b11110000
`define RM		8'b11111000
`define RST_0	8'b11000111
`define RST_1	8'b11001111
`define RST_2	8'b11010111
`define RST_3	8'b11011111
`define RST_4	8'b11100111
`define RST_5	8'b11101111
`define RST_6	8'b11110111
`define RST_7	8'b11111111
`define PCHL	8'b11101001
`define PUSH_B	8'b11000101
`define PUSH_D	8'b11010101
`define PUSH_H	8'b11100101
`define PUSH_PSW	8'b11110101
`define POP_B	8'b11000001
`define POP_D	8'b11010001
`define POP_H	8'b11100001
`define POP_PSW	8'b11110001
`define XTHL	8'b11100011
`define SPHL	8'b11111001
`define IN		8'b11011011
`define OUT		8'b11010011
`define EI		8'b11111011
`define DI		8'b11110011
`define HLT		8'b01110110
`define NOP		8'b00000000
`define LD_I_A	16'h47ED
`define LD_A_I	16'h57ED
`define IM0		16'h46ED
`define IM1		16'h56ED
`define IM2		16'h5EED
`define LDI_X	16'h2ADD
`define LDI_Y	16'h2AFD
`define LD_X_B	16'h70DD
`define LD_X_C	16'h71DD
`define LD_X_D	16'h72DD
`define LD_X_E	16'h73DD
`define LD_X_H	16'h74DD
`define LD_X_L	16'h75DD
`define LD_X_A	16'h77DD
`define LD_B_X	16'h46DD
`define LD_C_X	16'h4EDD
`define LD_D_X	16'h56DD
`define LD_E_X	16'h5EDD
`define LD_H_X	16'h66DD
`define LD_L_X	16'h6EDD
`define LD_A_X	16'h7EDD

`define LD_Y_B	16'h70FD
`define LD_Y_C	16'h71FD
`define LD_Y_D	16'h72FD
`define LD_Y_E	16'h73FD
`define LD_Y_H	16'h74FD
`define LD_Y_L	16'h75FD
`define LD_Y_A	16'h77FD
`define LD_B_Y	16'h46FD
`define LD_C_Y	16'h4EFD
`define LD_D_Y	16'h56FD
`define LD_E_Y	16'h5EFD
`define LD_H_Y	16'h66FD
`define LD_L_Y	16'h6EFD
`define LD_A_Y	16'h7EFD
`define LDI		16'hA0ED
`define LDIR	16'hB0ED
`define LDD		16'hA8ED
`define LDDR	16'hB8ED
`define Z80_CPI		16'hA1ED
`define Z80_CPIR	16'hB1ED
`define Z80_CPD		16'hA9ED
`define Z80_CPDR	16'hB9ED

lab_1/mem.v
`timescale 1ns/100ps
`include "../tv80_lib/8085_instr_set.v"
module RAM_4K(A, nOE, nWE, nCS, DQ);

input [11:0] A;
input nOE, nWE, nCS;
inout [7:0] DQ;

reg [7:0] MEM [4095:0];

//TODO: Implement 4kB RAM with task for loading a content using semi assembler

always @(nOE or nWE or nCS or DQ or A)
begin
    if(~nCS & ~nWE & nOE) begin
        MEM[A] = DQ;
    end
end 
assign DQ = (~nCS & nWE & ~nOE) ? MEM[A] : 8'hzz;
//---------------------------------------------------------
// Modelling tasks
//---------------------------------------------------------

reg [23:0] LABEL_r; 
integer wr_addr = 0; /* current write address */
reg [6:0] label_id;

//////////////////////////////////////////////////////////////////////////
// ASSIGN_LABEL
//////////////////////////////////////////////////////////////////////////
task ASSIGN_LABEL; /* Write byte to the memory */
input [23:0] LABEL;
begin
    LABEL_r = LABEL;
end
endtask

//////////////////////////////////////////////////////////////////////////
// WR_MEM
//////////////////////////////////////////////////////////////////////////
task WR_MEM; /* Write byte to the memory */
input [7:0] DATA;
begin
        MEM[wr_addr[11:0]] = DATA;
        wr_addr++;
end
endtask


//////////////////////////////////////////////////////////////////////////
// WR_MEM_W
//////////////////////////////////////////////////////////////////////////
task WR_MEM_W; /* Write word to the memory array */
input [15:0] DATA;
begin
    MEM[wr_addr[11:0]] = DATA[7:0];
    wr_addr++;
    MEM[wr_addr[11:0]] = DATA[15:8];
end
endtask


//////////////////////////////////////////////////////////////////////////
// INIT_MEM
//////////////////////////////////////////////////////////////////////////
task INIT_MEM; /* Initialize memory with provided value in every cell*/
input [7:0] DATA;
begin
        wr_addr = 'b0;
        while (wr_addr < 4095) begin
        MEM[wr_addr[11:0]] = DATA;
        wr_addr++;
        end 
        wr_addr = 'b0;
end 
endtask

//////////////////////////////////////////////////////////////////////////
// INSERT
//////////////////////////////////////////////////////////////////////////
task INSERT(
    input [15:0] DATA,
    input [15:0] IDX
);
begin
    MEM[IDX] <= DATA;
end

endtask

endmodule

lab_1/timer.sv
`timescale 1ns / 100ps
module TIMER #(
    parameter [15:0] MAX_VAL = 2** 16 
) (
    input CLK,
    input RSTn,
    input CE,
    output nINT
);

reg [15:0] TIMER_val;
logic nINT_r;

wire TIMER_LESS_THAN_MAX = TIMER_val < MAX_VAL;

always @(posedge CLK or negedge RSTn) begin
    if (!RSTn) begin
        TIMER_val <= 16'd0;
        nINT_r <= 1'b1;
    end
    else begin
        if (CE && TIMER_LESS_THAN_MAX) begin
            TIMER_val +=16'd1;
        end
        if (!TIMER_LESS_THAN_MAX) begin
            nINT_r <= 1'b0;
        end 

    end
end

assign nINT = nINT_r;
endmodule

lab_1/IO.sv
// `timescale 1ns / 100ps
// module IO (
//     input  nWR,      
//     input  nIORQ,    
//     input  nRD,      
//     inout  [7:0] DQ  
// );

//     logic [7:0] internal_data = 8'b0;  

//     wire rd_en = !nIORQ && !nRD;  
//     wire wr_en = !nIORQ && !nWR;  

//     always @(negedge nWR) begin
//         if (wr_en) begin
//             internal_data <= DQ;
//         end
//     end

// assign DQ = (rd_en)? internal_data : 8'bz;
// endmodule

`timescale 1ns / 100ps

module IO (
    input CLK,
    input [15:0] ADDR,
    input nIORQ,
    input nRD,
    input nWR,
    inout [7:0] DQ,
    inout nWAIT
);

reg [7:0] io_ports [3:0];
reg [7:0] data;
wire rd_en = !nIORQ && !nRD;  
wire wr_en = !nIORQ && !nWR;  
always @(posedge CLK)
begin
    if (rd_en) begin
        data <= io_ports[ADDR];
    end
    else if (wr_en) begin
        io_ports[ADDR] <= data;
    end
end

assign DQ = data;

task WRITE(
    input [15:0] ADDR,
    input [7:0] DQ
);
begin
    io_ports[ADDR] <= DQ;
end

endtask

endmodule

lab_1/BFM.sv
`timescale 1ns / 100ps

module BFM (
    input CLK,
    input CE,
    input nINT,
    input nWAIT,
    input nBUSRQ,
    output nBUSAK,
    input nCLR,
    output [15:0] ADDR,
    inout [7:0] D,
    output nMREQ,
    output nIORQ,
    output nM1,
    output nRD,
    output nWR,
    output [2:0] TS
  );

  reg nIORQ_r;
  reg nM1_r;
  reg nRD_r;
  reg nWR_r;
  reg nMREQ_r;
  reg [2:0] TS_r;
  reg [15:0] ADDR_r;
  reg nBUSAK_r;

  reg [7:0] D_r;

  assign ADDR = ADDR_r;
  assign TS = TS_r;
  assign nIORQ = nIORQ_r;
  assign nMREQ = nMREQ_r;
  assign nRD = nRD_r;
  assign nWR = nWR_r;
  assign nM1 = nM1_r;
  assign nBUSAK = nBUSAK_r;

   
  initial
  begin
    nM1_r = 1'b1;
    nWR_r = 1'b1;
    nRD_r = 1'b1;
    nIORQ_r = 1'b1;
    TS_r = 3'b000;
    nBUSAK_r = 1'b1;
    nMREQ_r = 1'b1;
    D_r = 8'd0;
  end

  task FETCH (
      input [15:0] ADDR,
      output [7:0] D
    );
    begin
      TS_r = 3'b001;
      nM1_r = 1'b0;
      ADDR_r = ADDR;
      @(negedge CLK);
      TS_r = 3'b010;
      nRD_r = 1'b0;
      nMREQ_r = 1'b0;
      D = D ; // TODO : Check for result of this cause this may indicate error
      @(negedge CLK);
      TS_r = 3'b011;
      nMREQ_r = 1'b1;
      nM1_r = 1'b1;
      nRD_r = 1'b1;
      @(negedge CLK);
      TS_r = 3'b100;
      @(negedge CLK);
    end
  endtask

  task MEMRD
    (
      input [15:0] ADDR,
      output [7:0] D
    );

    begin
      TS_r = 3'b001;
      ADDR_r = ADDR;
      D = 8'd0;
      @(negedge CLK);
      TS_r = 3'b010;
      nRD_r = 1'b0;
      nMREQ_r = 1'b0;
      D = D ; // TODO : Check for result of this cause this may indicate error
      @(negedge CLK);
      TS_r = 3'b011;
      nRD_r = 1'b1;
      nMREQ_r = 1'b1;
      D = 8'd0;
      @(negedge CLK);
    end
  endtask

  task MEMWR(
      input [15:0] ADDR,
      input [7:0] D_in
    );
    begin
    TS_r = 3'b001;
    ADDR_r = ADDR;
    D_r = D_in;
    @(negedge CLK);
    TS_r = 3'b010;
    nMREQ_r = 1'b0;
    nWR_r = 1'b0;
    @(negedge CLK);
    TS_r = 3'b011;
    nMREQ_r = 1'b1;
    nWR_r = 1'b1;
    @(negedge CLK);
    end
  endtask

  task IOR
    (
      input [15:0] ADDR,
      output [7:0] D
    );

    begin
      TS_r = 3'b001;
      ADDR_r = ADDR;
      D = 8'd0;
      @(negedge CLK);
      TS_r = 3'b010;
      D = D;
      nIORQ_r = 1'b0;
      nRD_r = 1'b0;
      @(negedge CLK);
      TS_r = 3'b011;
      D = 8'd0;
      nIORQ_r = 1'b1;
      nRD_r = 1'b1;
      @(negedge CLK);
    end
  endtask

  task IOW (
      input [15:0] ADDR,
      input [7:0] D_in
    );
    begin
      TS_r = 3'b001;
      ADDR_r = ADDR;
      D_r = D_in;
      @(negedge CLK);
      TS_r = 3'b010;
      nIORQ_r = 1'b0;
      nWR_r = 1'b0;
      @(negedge CLK);
      TS_r = 3'b011;
      nIORQ_r = 1'b1;
      nWR_r = 1'b1;
      @(negedge CLK);
    end
  endtask

  task INTERRUPT (
      input [15:0] ADDR,
      output [7:0] D
    );
    begin
      TS_r = 3'b001;
      nM1_r = 1'b0;
      ADDR_r = ADDR;
      @(negedge CLK);
      TS_r = 3'b010;
      nRD_r = 1'b0;
      nMREQ_r = 1'b0;
      D = D ; // TODO : Check for result of this cause this may indicate error
      @(negedge CLK);
      TS_r = 3'b011;
      nMREQ_r = 1'b1;
      nM1_r = 1'b1;
      nRD_r = 1'b1;
      @(negedge CLK);
      TS_r = 3'b100;
      @(negedge CLK);
    end
  endtask
endmodule

lab_1/ex1.sv
//-----------------------------------------------------------------------------
//
// Description : Z80 Test unit
//
//-----------------------------------------------------------------------------

`timescale 1ns / 100ps
`include "../tv80_lib/8085_instr_set.v"
module EX1_tb;

//Internal signals declarations:
reg CLK;
reg nCLR;
reg CE;
wire [15:0]ADDR;
//reg [7:0]DI;
wire [7:0] DQ;
wire nRD;
wire nWR;
wire nMREQ;
wire nIORQ;
wire nM1;
wire nWAIT;
reg nBUSRQ;
wire nINT;
wire [2:0] TS;

// Unit Under Test port map
// TV80_CPU
// 	#(.RESET_VECTOR(16'h0000))
// CPU_0 (
// 	.CLK(CLK),
// 	.nCLR(nCLR),
// 	.CE(CE),
// 	.ADDR(ADDR),
// 	.DQ(DQ),
// 	.nRD(nRD),
// 	.nWR(nWR),
// 	.nMREQ(nMREQ),
// 	.nIORQ(nIORQ),
// 	.nINT(nINT),
// 	.nNMI(1'b1),
// 	.nBUSRQ(nBUSRQ),
// 	.nBUSAK(),
// 	.nWAIT(nWAIT),
// 	.nM1(nM1),
// 	.TS(TS));
BFM BFM_inst (
	.CLK(CLK),
    .CE(CE),
    .nINT(nINT),
    .nWAIT(nWAIT),
    .nBUSRQ(nBUSRQ),
    .nBUSAK(),
    .nCLR(nCLR),
    .ADDR(ADDR),
    .D(DQ),
    .nMREQ(nMREQ),
    .nIORQ(nIORQ),
    .nM1(nM1),
    .nRD(nRD),
    .nWR(nWR),
    .TS(TS)
);

// IO IO_inst (
//     .nWR(nWR),      
//     .nIORQ(nIORQ),    
//     .nRD(nRD),      
//     .DQ(DQ)  
// );

IO IO_inst (
	.CLK(CLK),
	.ADDR(ADDR),
	.nWAIT(nWAIT),
    .nWR(nWR),      
    .nIORQ(nIORQ),    
    .nRD(nRD),      
    .DQ(DQ)  
);


TIMER #(
	.MAX_VAL(16'd400)
) TIMER_inst (
	.CLK(CLK),
    .RSTn(nCLR),
    .CE(CE),
    .nINT(nINT)
);



wire RAM_4K_CS = ~(~nMREQ & ~ADDR[15] & ~ADDR[14] & ~ADDR[13] & ~ADDR[12]);

RAM_4K M0(
	.A(ADDR[11:0]),
	.nOE(nRD),
	.nWE(nWR),
	.nCS(RAM_4K_CS),
	.DQ(DQ));


//Print out registers content at beginning of machine cycle
always @(negedge nM1) begin
	//TODO:: Fill code
end

//Stop simulation when IO write -> IO:0x80 = 0xFF
always @(posedge CLK) begin

end

initial	begin
	CLK = 1'b0;
	forever #5 CLK = ~CLK;
end

assign nWAIT = 1'b1; //No WAIT - Run with full speed

reg [23:0] MAIN_STOP;
// initial begin
// 	CE = 0;
// 	nCLR = 0;
// 	nINT = 1;
// 	nBUSRQ = 1'b1;
// 	WAIT(5);
// 	nBUSRQ = 1'b0;
// 	nCLR = 1;
// 	WAIT(5);
// 	// Feeding memory with operations 
// 	M0.WR_MEM(`LXI_SP); M0.WR_MEM_W(16'h800); //Initialize memory 
// 	M0.WR_MEM(`MVI_A); M0.WR_MEM(8'd12);
// 	M0.WR_MEM(`DAD_H); //RES = 2RES
// 	M0.WR_MEM(`RLC);
// 	WAIT(5);
// 	CE = 1;
// 	WAIT(50);
// 	// nBUSRQ = 1'b0;
// 	nINT = 0;
// 	WAIT(3);
// 	nBUSRQ = 1'b1;
// 	nINT = 1;
// 	WAIT(50);
// 	WAIT(50);
// 	nINT = 0;
// 	WAIT(3);
// 	nINT = 1;
// 	WAIT(50);
// 	$display("@%d: Simulation completed.", $time);
// 	$finish;
// end 
reg [ 15:0] ADDR_r = 16'd0;
reg [7:0] DQ_r;
initial begin
	CE = 0;
	nCLR = 0;
	// nINT = 1;
	nBUSRQ = 1'b1;
	WAIT(1);
	nBUSRQ = 1'b0;
	nCLR = 1;
	WAIT(1);
	CE=1;
	
	// Feeding memory with operations 
	M0.WR_MEM(`LXI_SP); 
	IO_inst.WRITE(16'b1000000000000000,8'b00000001);
	WAIT(1);
	IO_inst.WRITE(16'b0100000000000000,8'b00000010);
	M0.WR_MEM_W(16'h800); //Initialize memory 
	WAIT(1);
	IO_inst.WRITE(16'b0010000000000000,8'b00000100);
	M0.WR_MEM(`MVI_A);
	WAIT(1);
	IO_inst.WRITE(16'b0001000000000000,8'b00001000);
	M0.WR_MEM(8'd12);
	WAIT(1);
	M0.WR_MEM(`DAD_H); //RES = 2RES
	WAIT(1);
	M0.WR_MEM(`RLC);
	WAIT(1);

	BFM_inst.FETCH(ADDR_r, DQ_r);
	BFM_inst.MEMRD(ADDR_r, DQ_r);
	BFM_inst.MEMWR(ADDR_r, 8'b00000001);
	BFM_inst.IOR(ADDR_r, DQ_r);
	BFM_inst.IOW(ADDR_r, 8'b00000001);
	ADDR_r = ADDR_r + 1'b1;
	
	BFM_inst.FETCH(ADDR_r, DQ_r);
	BFM_inst.MEMRD(ADDR_r, DQ_r);
	BFM_inst.MEMWR(ADDR_r, 8'b00000010);
	BFM_inst.IOR(16'b1000000000000000, DQ_r);
	BFM_inst.IOW(16'b1000000000000000, 8'b00000010);
	ADDR_r = ADDR_r + 1'b1;
	
	BFM_inst.FETCH(ADDR_r, DQ_r);
	BFM_inst.MEMRD(ADDR_r, DQ_r);
	BFM_inst.MEMWR(ADDR_r, 8'b00000011);
	BFM_inst.IOR(16'b0100000000000000, DQ_r);
	BFM_inst.IOW(16'b0100000000000000, 8'b00000011);
	ADDR_r = ADDR_r + 1'b1;
	
	BFM_inst.FETCH(ADDR_r, DQ_r);
	BFM_inst.MEMRD(ADDR_r, DQ_r);
	BFM_inst.MEMWR(ADDR_r, 8'b00000100);
	BFM_inst.IOR(16'b0010000000000000, DQ_r);
	BFM_inst.IOW(16'b0010000000000000, 8'b00000100);
	ADDR_r = ADDR_r + 1'b1;

	$display("@%d: Simulation completed.", $time);
	$finish;
end 

initial begin
	$dumpfile("ex1.vcd");
	$dumpvars(0, EX1_tb);
	$dumpon;
end

//---------------------------------------------------------
//  Included program - use memory tasks to prepare the program
//---------------------------------------------------------

//`include "tv80_mul.v"

task WAIT;
input [31:0] dy;
begin
	repeat(dy)
	@(negedge CLK);
end
endtask

endmodule

lab_1/ex1.vcd
$date
	Wed Nov  6 16:26:21 2024
$end
$version
	Icarus Verilog
$end
$timescale
	100ps
$end
$scope module EX1_tb $end
$var wire 8 ! DQ [7:0] $end
$var wire 1 " RAM_4K_CS $end
$var wire 1 # nWAIT $end
$var wire 1 $ nWR $end
$var wire 1 % nRD $end
$var wire 1 & nMREQ $end
$var wire 1 ' nM1 $end
$var wire 1 ( nIORQ $end
$var wire 1 ) nINT $end
$var wire 3 * TS [2:0] $end
$var wire 16 + ADDR [15:0] $end
$var reg 16 , ADDR_r [15:0] $end
$var reg 1 - CE $end
$var reg 1 . CLK $end
$var reg 8 / DQ_r [7:0] $end
$var reg 1 0 nBUSRQ $end
$var reg 1 1 nCLR $end
$scope module BFM_inst $end
$var wire 1 - CE $end
$var wire 1 . CLK $end
$var wire 8 2 D [7:0] $end
$var wire 3 3 TS [2:0] $end
$var wire 1 4 nBUSAK $end
$var wire 1 0 nBUSRQ $end
$var wire 1 1 nCLR $end
$var wire 1 ' nM1 $end
$var wire 1 # nWAIT $end
$var wire 1 $ nWR $end
$var wire 1 % nRD $end
$var wire 1 & nMREQ $end
$var wire 1 ( nIORQ $end
$var wire 1 ) nINT $end
$var wire 16 5 ADDR [15:0] $end
$var reg 16 6 ADDR_r [15:0] $end
$var reg 8 7 D_r [7:0] $end
$var reg 3 8 TS_r [2:0] $end
$var reg 1 9 nBUSAK_r $end
$var reg 1 ( nIORQ_r $end
$var reg 1 : nM1_r $end
$var reg 1 & nMREQ_r $end
$var reg 1 % nRD_r $end
$var reg 1 $ nWR_r $end
$scope task FETCH $end
$var reg 16 ; ADDR [15:0] $end
$var reg 8 < D [7:0] $end
$upscope $end
$scope task INTERRUPT $end
$var reg 16 = ADDR [15:0] $end
$var reg 8 > D [7:0] $end
$upscope $end
$scope task IOR $end
$var reg 16 ? ADDR [15:0] $end
$var reg 8 @ D [7:0] $end
$upscope $end
$scope task IOW $end
$var reg 16 A ADDR [15:0] $end
$var reg 8 B D_in [7:0] $end
$upscope $end
$scope task MEMRD $end
$var reg 16 C ADDR [15:0] $end
$var reg 8 D D [7:0] $end
$upscope $end
$scope task MEMWR $end
$var reg 16 E ADDR [15:0] $end
$var reg 8 F D_in [7:0] $end
$upscope $end
$upscope $end
$scope module IO_inst $end
$var wire 16 G ADDR [15:0] $end
$var wire 1 . CLK $end
$var wire 8 H DQ [7:0] $end
$var wire 1 ( nIORQ $end
$var wire 1 % nRD $end
$var wire 1 # nWAIT $end
$var wire 1 $ nWR $end
$var wire 1 I rd_en $end
$var wire 1 J wr_en $end
$var reg 8 K data [7:0] $end
$scope task WRITE $end
$var reg 16 L ADDR [15:0] $end
$var reg 8 M DQ [7:0] $end
$upscope $end
$upscope $end
$scope module M0 $end
$var wire 12 N A [11:0] $end
$var wire 8 O DQ [7:0] $end
$var wire 1 " nCS $end
$var wire 1 % nOE $end
$var wire 1 $ nWE $end
$var reg 24 P LABEL_r [23:0] $end
$var integer 32 Q wr_addr [31:0] $end
$scope task ASSIGN_LABEL $end
$var reg 24 R LABEL [23:0] $end
$upscope $end
$scope task INIT_MEM $end
$var reg 8 S DATA [7:0] $end
$upscope $end
$scope task INSERT $end
$var reg 16 T DATA [15:0] $end
$var reg 16 U IDX [15:0] $end
$upscope $end
$scope task WR_MEM $end
$var reg 8 V DATA [7:0] $end
$upscope $end
$scope task WR_MEM_W $end
$var reg 16 W DATA [15:0] $end
$upscope $end
$upscope $end
$scope module TIMER_inst $end
$var wire 1 - CE $end
$var wire 1 . CLK $end
$var wire 1 1 RSTn $end
$var wire 1 ) nINT $end
$var wire 1 X TIMER_LESS_THAN_MAX $end
$var reg 16 Y TIMER_val [15:0] $end
$var reg 1 Z nINT_r $end
$upscope $end
$scope task WAIT $end
$var reg 32 [ dy [31:0] $end
$upscope $end
$upscope $end
$enddefinitions $end
#0
$dumpvars
b1 [
1Z
b0 Y
1X
bx W
bx V
bx U
bx T
bx S
bx R
b0 Q
bx P
bx O
bx N
bx M
bx L
bx K
0J
0I
bx H
bx G
bx F
bx E
bx D
bx C
bx B
bx A
bx @
bx ?
bx >
bx =
bx <
bx ;
1:
19
b0 8
b0 7
bx 6
bx 5
14
b0 3
bx 2
01
10
bx /
0.
0-
b0 ,
bx +
b0 *
1)
1(
1'
1&
1%
1$
1#
1"
bx !
$end
#50
1.
#100
11
00
0.
#150
1.
#200
b1 M
b1000000000000000 L
b1 Q
b110001 V
1-
0.
#250
b1 Y
1.
#300
b10 Q
b100000000000 W
b10 M
b100000000000000 L
0.
#350
b10 Y
1.
#400
b11 Q
b111110 V
b100 M
b10000000000000 L
0.
#450
b11 Y
1.
#500
b100 Q
b1100 V
b1000 M
b1000000000000 L
0.
#550
b100 Y
1.
#600
b101 Q
b101001 V
0.
#650
b101 Y
1.
#700
b110 Q
b111 V
0.
#750
b110 Y
1.
#800
b0 N
b0 +
b0 5
b0 6
b0 G
0'
0:
b1 *
b1 3
b1 8
b0 ;
0.
#850
b111 Y
1.
#900
0"
0&
0%
b10 *
b10 3
b10 8
0.
#950
b1000 Y
1.
#1000
1"
1%
1'
1:
1&
b11 *
b11 3
b11 8
0.
#1050
b1001 Y
1.
#1100
b100 *
b100 3
b100 8
0.
#1150
b1010 Y
1.
#1200
b0 D
b1 *
b1 3
b1 8
b0 C
0.
#1250
b1011 Y
1.
#1300
0"
0&
0%
b10 *
b10 3
b10 8
0.
#1350
b1100 Y
1.
#1400
1"
1&
1%
b11 *
b11 3
b11 8
0.
#1450
b1101 Y
1.
#1500
b1 7
b1 *
b1 3
b1 8
b1 F
b0 E
b0 /
0.
#1550
b1110 Y
1.
#1600
0"
0$
0&
b10 *
b10 3
b10 8
0.
#1650
b1111 Y
1.
#1700
1"
1$
1&
b11 *
b11 3
b11 8
0.
#1750
b10000 Y
1.
#1800
b0 @
b1 *
b1 3
b1 8
b0 ?
0.
#1850
b10001 Y
1.
#1900
1I
0%
0(
b10 *
b10 3
b10 8
0.
#1950
b10010 Y
1.
#2000
0I
1%
1(
b11 *
b11 3
b11 8
0.
#2050
b10011 Y
1.
#2100
b1 *
b1 3
b1 8
b1 B
b0 A
0.
#2150
b10100 Y
1.
#2200
1J
0$
0(
b10 *
b10 3
b10 8
0.
#2250
b10101 Y
1.
#2300
0J
1$
1(
b11 *
b11 3
b11 8
0.
#2350
b10110 Y
1.
#2400
b1 N
b1 +
b1 5
b1 6
b1 G
0'
0:
b1 *
b1 3
b1 8
b1 ;
b1 ,
0.
#2450
b10111 Y
1.
#2500
0"
0&
0%
b10 *
b10 3
b10 8
0.
#2550
b11000 Y
1.
#2600
1"
1%
1'
1:
1&
b11 *
b11 3
b11 8
0.
#2650
b11001 Y
1.
#2700
b100 *
b100 3
b100 8
0.
#2750
b11010 Y
1.
#2800
b1 *
b1 3
b1 8
b1 C
bx /
0.
#2850
b11011 Y
1.
#2900
0"
0&
0%
b10 *
b10 3
b10 8
0.
#2950
b11100 Y
1.
#3000
1"
1&
1%
b11 *
b11 3
b11 8
0.
#3050
b11101 Y
1.
#3100
b10 7
b1 *
b1 3
b1 8
b10 F
b1 E
b0 /
0.
#3150
b11110 Y
1.
#3200
0"
0$
0&
b10 *
b10 3
b10 8
0.
#3250
b11111 Y
1.
#3300
1"
1$
1&
b11 *
b11 3
b11 8
0.
#3350
b100000 Y
1.
